Metadata-Version: 2.1
Name: mmysql
Version: 1.0
Summary: mysql工具类
Home-page: UNKNOWN
Author: Lsw
License: UNKNOWN
Platform: all
Classifier: Programming Language :: Python :: 3
Classifier: License :: OSI Approved :: MIT License
Classifier: Operating System :: OS Independent
Requires-Python: >2
